popui/__init__.py
popui/clipboard.py
popui/example.py
popui/keys.py
popui/popup.py
popui-0.0.12.dist-info/METADATA
popui-0.0.12.dist-info/WHEEL
popui-0.0.12.dist-info/top_level.txt
popui-0.0.12.dist-info/RECORD
